gdsfactory_install/__init__.py
gdsfactory_install/config.py
gdsfactory_install/main.py
gdsfactory_install-0.0.5.dist-info/entry_points.txt
gdsfactory_install-0.0.5.dist-info/licenses/LICENSE
gdsfactory_install-0.0.5.dist-info/WHEEL
gdsfactory_install-0.0.5.dist-info/METADATA
gdsfactory_install-0.0.5.dist-info/RECORD
